music_parser/__init__.py
music_parser/midi_players.py
music_parser/piece_compiler.py
music_parser/presets.py
music_parser/columns/__init__.py
music_parser/columns/column.py
music_parser/columns/midi_columns.py
music_parser/tokenizers/__init__.py
music_parser/tokenizers/midi_tokenizer.py
music_parser/tokenizers/tokenizer.py
music_parser/tokenizers/tokenizer_funcs/__init__.py
music_parser/tokenizers/tokenizer_funcs/midi_funcs.py
music_parser-0.0.4.dist-info/LICENSE
music_parser-0.0.4.dist-info/METADATA
music_parser-0.0.4.dist-info/WHEEL
music_parser-0.0.4.dist-info/top_level.txt
music_parser-0.0.4.dist-info/RECORD
