Metadata-Version: 2.1
Name: music-parser
Version: 0.0.4
Summary: Parsing tools for music generation
Home-page: https://github.com/noahsolomon0518/music-parser
Author: Noah Solomon
Author-email: noahsolomon0518@gmail.com
License: UNKNOWN
Project-URL: Bug Tracker, https://github.com/noahsolomon0518/music-parser/issues
Platform: UNKNOWN
Classifier: Programming Language :: Python :: 3
Classifier: License :: OSI Approved :: MIT License
Classifier: Operating System :: OS Independent
Requires-Python: >=3.8
License-File: LICENSE
